execlog/__init__.py
execlog/config.py
execlog/setlogs.py
execlog/tools.py
exec_log-0.1.8.dist-info/LICENSE
exec_log-0.1.8.dist-info/METADATA
exec_log-0.1.8.dist-info/WHEEL
exec_log-0.1.8.dist-info/top_level.txt
exec_log-0.1.8.dist-info/RECORD
