Metadata-Version: 2.1
Name: exec-log
Version: 0.1.8
Summary: Project logging
Home-page: https://github.com/supplayer/exec-log
Author: Supplayer
Author-email: x254724521@hotmail.com
License: UNKNOWN
Platform: UNKNOWN
Classifier: Programming Language :: Python :: 3
Classifier: License :: OSI Approved :: MIT License
Classifier: Operating System :: OS Independent
Requires-Python: >=3.6
License-File: LICENSE
Requires-Dist: loguru
Requires-Dist: CMRESHandler2
Requires-Dist: notifiers
